{"cameraMode":{"drawMode":0,"name":"Shaded","section":"Shading Mode"},"sceneLighting":true,"audioPlay":false,"sceneViewState":{"showFog":true,"showMaterialUpdate":false,"showSkybox":true,"showFlares":true,"showImageEffects":true,"showParticleSystems":true},"in2DMode":false,"pivot":{"x":-1.6169339418411255,"y":6.542061805725098,"z":-3.512465715408325},"rotation":{"x":0.4018811881542206,"y":0.085512176156044,"z":-0.03772766515612602,"w":0.9109119176864624},"size":4.752058982849121,"orthographic":false}